tljh_matlab/__init__.py
tljh_matlab/install_matlab.py
tljh_matlab/tljh_matlab.py
tljh_matlab/bash_scripts/install-matlab.sh
tljh_matlab-0.1.0.dist-info/LICENSE
tljh_matlab-0.1.0.dist-info/METADATA
tljh_matlab-0.1.0.dist-info/WHEEL
tljh_matlab-0.1.0.dist-info/entry_points.txt
tljh_matlab-0.1.0.dist-info/top_level.txt
tljh_matlab-0.1.0.dist-info/RECORD
