Metadata-Version: 2.1
Name: tljh-matlab
Version: 0.1.0
Summary: TLJH plugin for MATLAB
Home-page: https://github.com/mathworks/jupyter-matlab-proxy/tree/main/install_guides/the-littlest-jupyterhub/tljh-matlab
Author: The MathWorks, Inc.
Author-email: cloud@mathworks.com
License: MATHWORKS CLOUD REFERENCE ARCHITECTURE LICENSE
License-File: LICENSE
